{
  "people": {
    "p117": {"x": 6782.75, "y": 1295.9, "width": 230, "height": 28},
    "p118": {"x": 5387, "y": 1295.5, "width": 144.3, "height": 28},
    "p119": {"x": 7368.08, "y": 1295.9, "width": 119.8, "height": 28},
    "p120": {"x": 7654.58, "y": 1295.9, "width": 230, "height": 28},
    "p128": {"x": 3059.01, "y": 1295.9, "width": 188.4, "height": 28},
    "p129": {"x": 5180, "y": 1295.5, "width": 188.4, "height": 28},
    "p130": {"x": 3762.48, "y": 1295.9, "width": 134.5, "height": 28},
    "p148": {"x": 3795, "y": 1998.13, "width": 149.2, "height": 28},
    "p149": {"x": 3075, "y": 1830.53, "width": 114.9, "height": 28},
    "p150": {"x": 3245, "y": 1998.13, "width": 119.8, "height": 28},
    "p151": {"x": 3410, "y": 1998.13, "width": 149.2, "height": 28},
    "p152": {"x": 2930, "y": 1998.13, "width": 114.9, "height": 28},
    "p153": {"x": 2790, "y": 1998.13, "width": 118.51, "height": 28},
    "p154": {"x": 2847.57, "y": 2154.94, "width": 141.56, "height": 28},
    "p155": {"x": 3580, "y": 1998.13, "width": 168.8, "height": 28},
    "p160": {"x": 4096.84, "y": 2154.94, "width": 119.8, "height": 28},
    "p161": {"x": 4204.33, "y": 2154.94, "width": 119.8, "height": 28},
    "p163": {"x": 4363.04, "y": 2154.94, "width": 159, "height": 28},
    "p164": {"x": 4534.09, "y": 2154.94, "width": 139.4, "height": 28},
    "p170": {"x": 4869.1, "y": 2154.94, "width": 129.6, "height": 28},
    "p171": {"x": 5007.4, "y": 2154.94, "width": 134.5, "height": 28},
    "p174": {"x": 5245.24, "y": 2154.94, "width": 183.5, "height": 28},
    "p175": {"x": 5396.44, "y": 2154.94, "width": 183.5, "height": 28},
    "p180": {"x": 6422.85, "y": 1997.37, "width": 135.09, "height": 28},
    "p182": {"x": 5692.28, "y": 2154.94, "width": 134.5, "height": 28},
    "p186": {"x": 6920, "y": 1997.37, "width": 173.7, "height": 28},
    "p187": {"x": 6567.7, "y": 1830.54, "width": 163.9, "height": 28},
    "p188": {"x": 6590, "y": 1997.37, "width": 119.8, "height": 28},
    "p189": {"x": 6750, "y": 1997.37, "width": 129.6, "height": 28},
    "p191": {"x": 7345, "y": 1997.37, "width": 119.8, "height": 28},
    "p192": {"x": 7505, "y": 1996, "width": 129.6, "height": 28},
    "p195": {"x": 7135, "y": 1997.37, "width": 168.8, "height": 28},
    "p196": {"x": 7405, "y": 2154.94, "width": 134.5, "height": 28},
    "p197": {"x": 3497.45, "y": 2154.94, "width": 154.1, "height": 28},
    "p198": {"x": 5835, "y": 2154.94, "width": 168.8, "height": 28},
    "p199": {"x": 6015, "y": 2154.94, "width": 159, "height": 28},
    "p200": {"x": 6205, "y": 2154.94, "width": 139.4, "height": 28},
    "p201": {"x": 3090, "y": 1998.13, "width": 134.5, "height": 28},
    "p202": {"x": 2890, "y": 1830.53, "width": 119.8, "height": 28}
  },
  "relationships": {
    "r34": {"x": 3395, "y": 1930},
    "r35": {"x": 2918.35, "y": 2060.13},
    "r36": {"x": 3574.5, "y": 2060.13},
    "r54": {"x": 7113.13, "y": 2025},
    "r55": {"x": 3231.08, "y": 2060.13},
    "r56": {"x": 3041.18, "y": 1892.61}
  }
}
